notecomputer/__init__.py
notecomputer/config/__init__.py
notecomputer/config/core.py
notecomputer/install/__init__.py
notecomputer/install/base.py
notecomputer/install/config.py
notecomputer/install/core_server.py
notecomputer/run/__init__.py
notecomputer/workspace/__init__.py
notecomputer/workspace/core.py
notecomputer-0.0.25.dist-info/METADATA
notecomputer-0.0.25.dist-info/WHEEL
notecomputer-0.0.25.dist-info/top_level.txt
notecomputer-0.0.25.dist-info/RECORD
