Metadata-Version: 2.1
Name: notecomputer
Version: 0.0.25
Summary: notecomputer
Home-page: https://github.com/1007530194
Author: niuliangtao
Author-email: 1007530194@qq.com
License: UNKNOWN
Platform: UNKNOWN
Requires-Dist: requests
Requires-Dist: demjson
Requires-Dist: tqdm
Requires-Dist: cryptography
Requires-Dist: pycurl
Requires-Dist: urllib3
Requires-Dist: notetool
Requires-Dist: requests-toolbelt
